binance_f/__init__.py
binance_f/requestclient.py
binance_f/subscriptionclient.py
binance_f/base/__init__.py
binance_f/base/printobject.py
binance_f/base/printtime.py
binance_f/constant/__init__.py
binance_f/constant/system.py
binance_f/constant/test.py
binance_f/exception/__init__.py
binance_f/exception/binanceapiexception.py
binance_f/impl/__init__.py
binance_f/impl/restapiinvoker.py
binance_f/impl/restapirequest.py
binance_f/impl/restapirequestimpl.py
binance_f/impl/tradeServer.py
binance_f/impl/websocketconnection.py
binance_f/impl/websocketrequest.py
binance_f/impl/websocketrequestimpl.py
binance_f/impl/websocketwatchdog.py
binance_f/impl/utils/__init__.py
binance_f/impl/utils/apisignature.py
binance_f/impl/utils/channelparser.py
binance_f/impl/utils/channels.py
binance_f/impl/utils/inputchecker.py
binance_f/impl/utils/jsonwrapper.py
binance_f/impl/utils/timeservice.py
binance_f/impl/utils/urlparamsbuilder.py
binance_f/model/__init__.py
binance_f/model/accountinformation.py
binance_f/model/accountupdate.py
binance_f/model/aggregatetrade.py
binance_f/model/aggregatetradeevent.py
binance_f/model/balance.py
binance_f/model/candlestick.py
binance_f/model/candlestickevent.py
binance_f/model/codeandmsg.py
binance_f/model/constant.py
binance_f/model/diffdepthevent.py
binance_f/model/exchangeinformation.py
binance_f/model/fundingrate.py
binance_f/model/income.py
binance_f/model/leverage.py
binance_f/model/liquidationorder.py
binance_f/model/liquidationorderevent.py
binance_f/model/listenkeyexpired.py
binance_f/model/markprice.py
binance_f/model/markpriceevent.py
binance_f/model/message.py
binance_f/model/mytrade.py
binance_f/model/openinterest.py
binance_f/model/order.py
binance_f/model/orderbook.py
binance_f/model/orderbookevent.py
binance_f/model/orderupdate.py
binance_f/model/position.py
binance_f/model/positionmargin.py
binance_f/model/positionmarginhistory.py
binance_f/model/positionmode.py
binance_f/model/symbolbooktickerevent.py
c_binance_future_quant-1.1.5.dist-info/LICENSE
c_binance_future_quant-1.1.5.dist-info/METADATA
c_binance_future_quant-1.1.5.dist-info/WHEEL
c_binance_future_quant-1.1.5.dist-info/top_level.txt
c_binance_future_quant-1.1.5.dist-info/RECORD
