Metadata-Version: 2.1
Name: c-binance-future-quant
Version: 1.1.5
Summary: 这是一套经过长时间实盘验证，有超过100亿美金交易量，包含币安合约的数据录入，风控，交易的架构实现，但不包含具体的策略，仅提供一个简单的交易实践演示数据读取，开仓，平仓，以及止盈止损，风控，还有前端数据展示和分析（前端板块为react+redux+antd，开源还在准备中，因为现在还有维护一个左侧策略，打算直接把这个左侧策略的数据释放出来示范，应该在7月25号前发布上来）你可以利用它简单，低成本的实现你的交易逻辑，其大量运用阿里云服务器进行分布式架构，多进程处理，以及飞书进行异常报错和交易信息披露...如果你愿意详细阅读该readme的所有信息，尤其是 [模块详细解析](#模块详细解析) ，那么他同时也会是一部关于币安合约的交易风控，设计架构的经验理解历史，总结了几乎本人所有成功和失败的经验，希望能让后人少踩些坑
Home-page: https://github.com/yanjlee/c-binance-future-quant
Author: yanjlee
Author-email: yanjlee@163.com
Classifier: Programming Language :: Python :: 3
Classifier: License :: OSI Approved :: MIT License
Classifier: Operating System :: OS Independent
License-File: LICENSE
Requires-Dist: requests
Requires-Dist: faker
Requires-Dist: execjs
Requires-Dist: loguru
Requires-Dist: base64
Requires-Dist: hashlib
Requires-Dist: Crypto
Requires-Dist: pandas
Requires-Dist: fuzzywuzzy
Requires-Dist: httpx
Requires-Dist: Pillow
Requires-Dist: playwright
Requires-Dist: PyExecJS
Requires-Dist: redis
Requires-Dist: fastapi
Requires-Dist: uvicorn
Requires-Dist: APScheduler
Requires-Dist: beautifulsoup4
Requires-Dist: bs4
Requires-Dist: certifi
Requires-Dist: clickhouse-driver
Requires-Dist: curl-cffi
Requires-Dist: DrissionPage
Requires-Dist: fake-useragent
Requires-Dist: Flask
Requires-Dist: Flask-APScheduler
Requires-Dist: Flask-Cors
Requires-Dist: frida
Requires-Dist: gevent
Requires-Dist: Jinja2
Requires-Dist: langchain
Requires-Dist: langchain-community
Requires-Dist: suiutils-py
